asyncval/__init__.py
asyncval/__main__.py
asyncval/arguments.py
asyncval/callbacks.py
asyncval/data.py
asyncval/evaluation.py
asyncval/modeling.py
asyncval/retriever.py
asyncval/splitter.py
asyncval-0.2.0.dist-info/LICENSE
asyncval-0.2.0.dist-info/METADATA
asyncval-0.2.0.dist-info/WHEEL
asyncval-0.2.0.dist-info/top_level.txt
asyncval-0.2.0.dist-info/RECORD
