Metadata-Version: 2.1
Name: asyncval
Version: 0.2.0
Summary: Asyncval: A toolkit for asynchronously validating dense retriever checkpoints during training.
Home-page: https://github.com/ielab/asyncval
Author: Shengyao Zhuang
Author-email: s.zhuang@uq.edu.au
License: Apache 2.0
Platform: UNKNOWN
Requires-Python: >=3.7
Requires-Dist: transformers (>=4.10.0)
Requires-Dist: datasets (>=1.1.3)
